oneclicksetup/__init__.py
oneclicksetup/cli.py
oneclicksetup/env_utils.py
oneclicksetup-0.1.0.dist-info/METADATA
oneclicksetup-0.1.0.dist-info/WHEEL
oneclicksetup-0.1.0.dist-info/entry_points.txt
oneclicksetup-0.1.0.dist-info/top_level.txt
oneclicksetup-0.1.0.dist-info/RECORD
