Metadata-Version: 2.2
Name: oneclicksetup
Version: 0.1.0
Summary: A one-click environment setup CLI.
Author-email: Your Name <you@example.com>
Keywords: cli,devops,setup
Classifier: Programming Language :: Python :: 3
Classifier: Operating System :: OS Independent
Requires-Python: >=3.6
Requires-Dist: python-dotenv==0.21.0
